fasttext_parallel-0.1.4.dist-info/METADATA
fasttext_parallel-0.1.4.dist-info/WHEEL
fasttext_parallel-0.1.4.dist-info/license_files/LICENSE
fasttext_parallel/fasttext_parallel.pyi
fasttext_parallel/py.typed
fasttext_parallel/__init__.py
fasttext_parallel/fasttext_parallel.cp38-win32.pyd
fasttext_parallel-0.1.4.dist-info/RECORD
